ChemE/Boiler.py
ChemE/HMT.py
ChemE/Thermo.py
ChemE/__init__.py
ChemE/Data_files/CP_gases.txt
ChemE/Data_files/HR0.txt
ChemE/Data_files/HR1.txt
ChemE/Data_files/Lee_Kesler_Z0.txt
ChemE/Data_files/Lee_Kesler_Z1.txt
ChemE/Data_files/SR0.txt
ChemE/Data_files/SR1.txt
ChemE/Data_files/Superheat.txt
ChemE/Data_files/Table_B1.txt
ChemE/Data_files/Table_B2.txt
ChemE/Data_files/Table_C4.txt
ChemE/Data_files/Table_E1.txt
ChemE/Data_files/phi0.txt
ChemE/Data_files/phi1.txt
ChemE-0.7.1.dist-info/LICENSE
ChemE-0.7.1.dist-info/METADATA
ChemE-0.7.1.dist-info/WHEEL
ChemE-0.7.1.dist-info/top_level.txt
ChemE-0.7.1.dist-info/RECORD
