Metadata-Version: 2.1
Name: ChemE
Version: 0.7.1
Summary: Various functions and data for Chemical Engineering Students
Home-page: https://github.com/ConciseVerbosity18/ChemE_CV
Author: ol-<(
License: MIT
Platform: UNKNOWN
Classifier: License :: OSI Approved :: MIT License
Classifier: Programming Language :: Python :: 3.7
Classifier: Programming Language :: Python :: 3.8
Classifier: Programming Language :: Python :: 3.9
Requires-Dist: numpy
Requires-Dist: scipy
Requires-Dist: pandas
Requires-Dist: matplotlib
Requires-Dist: prettytable
Requires-Dist: pyXSteam
Requires-Dist: PySimpleGUI
Requires-Dist: wmi
Requires-Dist: pygetwindow
